{
    "class": "0",
    "bbox": [
        140.99290466308594,
        1292.357421875,
        1238.2664794921875,
        2145.672119140625
    ],
    "conf": 0.8888562321662903,
    "bbox_normalized": [
        0.055291335161994484,
        0.3916234611742424,
        0.48559469784007353,
        0.6502036724668561
    ],
    "center": [
        689.6296920776367,
        1719.0147705078125
    ],
    "center_normalized": [
        0.27044301650103403,
        0.5209135668205492
    ],
    "legend_boxes": [
        {
            "class": "legend_box",
            "bbox": [
                158.32708740234375,
                46.791446685791016,
                308.0692138671875,
                155.06869506835938
            ],
            "conf": 0.9604344367980957,
            "bbox_normalized": [
                0.14419589016606899,
                0.054855154379590876,
                0.2805730545238502,
                0.1817921395877601
            ]
        }
    ],
    "labels": [
        {
            "class": "plot_area",
            "bbox": [
                139.45086669921875,
                34.347110748291016,
                1055.737548828125,
                657.44580078125
            ],
            "conf": 0.8922294974327087,
            "bbox_normalized": [
                0.12700443233080033,
                0.04026624941183003,
                0.9615096073115893,
                0.7707453702007621
            ]
        },
        {
            "class": "x_axis",
            "bbox": [
                119.59008026123047,
                666.0045166015625,
                1077.9200439453125,
                750.8341674804688
            ],
            "conf": 0.6621376276016235,
            "bbox_normalized": [
                0.10891628439092028,
                0.7807790347028869,
                0.9817122440303393,
                0.8802276289337265
            ]
        },
        {
            "class": "y_axis",
            "bbox": [
                19.888708114624023,
                26.293651580810547,
                128.8330841064453,
                660.2327270507812
            ],
            "conf": 0.5513006448745728,
            "bbox_normalized": [
                0.018113577517872518,
                0.03082491392826559,
                0.11733432067982269,
                0.7740125756750074
            ]
        },
        {
            "class": "x_axis",
            "bbox": [
                162.48060607910156,
                790.158447265625,
                933.0921630859375,
                843.3302612304688
            ],
            "conf": 0.5443843603134155,
            "bbox_normalized": [
                0.14797869406111253,
                0.9263287775681418,
                0.8498107131930214,
                0.9886638466945706
            ]
        }
    ]
}