{
    "class": 1,
    "bbox": [
        130.4396514892578,
        361.0687255859375,
        1262.4429931640625,
        1154.7718505859375
    ],
    "bbox_normalized": [
        0.0511528045055913,
        0.10941476532907198,
        0.49507568359375,
        0.34993086381392047
    ],
    "conf": 0.9377281069755554,
    "center": [
        696.4413223266602,
        757.9202880859375
    ],
    "center_normalized": [
        0.27311424404967066,
        0.22967281457149621
    ],
    "legend_boxes": [
        {
            "class": "legend_box",
            "bbox": [
                926.058349609375,
                52.9908447265625,
                1074.815185546875,
                137.57554626464844
            ],
            "bbox_normalized": [
                0.8180727470047482,
                0.06682325942819987,
                0.9494833794583701,
                0.1734874480008177
            ],
            "conf": 0.8877249956130981
        }
    ],
    "labels": [
        {
            "class": "plot_area",
            "bbox": [
                134.41189575195312,
                35.34941482543945,
                1083.6060791015625,
                679.0093383789062
            ],
            "bbox_normalized": [
                0.11873842380914587,
                0.04457681566890221,
                0.9572491864854792,
                0.8562538945509537
            ],
            "conf": 0.9199931621551514
        },
        {
            "class": "x_axis",
            "bbox": [
                118.75843048095703,
                690.8881225585938,
                1106.489990234375,
                771.0294189453125
            ],
            "bbox_normalized": [
                0.10491027427646381,
                0.8712334458494246,
                0.9774646556840768,
                0.9722943492374685
            ],
            "conf": 0.66172856092453
        },
        {
            "class": "y_axis",
            "bbox": [
                26.132862091064453,
                26.538562774658203,
                125.27136993408203,
                694.8135986328125
            ],
            "bbox_normalized": [
                0.02308556721825482,
                0.03346603124168752,
                0.11066375435872972,
                0.876183604833307
            ],
            "conf": 0.5951060056686401
        }
    ],
    "lines": [
        [
            [
                9,
                32
            ],
            [
                10,
                32
            ],
            [
                11,
                32
            ],
            [
                12,
                32
            ],
            [
                13,
                32
            ],
            [
                14,
                32
            ],
            [
                15,
                32
            ],
            [
                16,
                32
            ],
            [
                17,
                32
            ],
            [
                18,
                32
            ],
            [
                19,
                32
            ],
            [
                20,
                32
            ],
            [
                21,
                32
            ],
            [
                22,
                32
            ],
            [
                23,
                32
            ],
            [
                24,
                32
            ],
            [
                25,
                32
            ],
            [
                26,
                32
            ],
            [
                27,
                32
            ],
            [
                28,
                32
            ],
            [
                29,
                32
            ],
            [
                30,
                32
            ],
            [
                31,
                32
            ],
            [
                32,
                32
            ],
            [
                33,
                32
            ],
            [
                34,
                32
            ],
            [
                35,
                32
            ],
            [
                36,
                32
            ],
            [
                37,
                32
            ],
            [
                38,
                32
            ],
            [
                39,
                32
            ],
            [
                40,
                31
            ],
            [
                41,
                31
            ],
            [
                42,
                31
            ],
            [
                43,
                31
            ],
            [
                44,
                31
            ],
            [
                45,
                31
            ],
            [
                46,
                31
            ],
            [
                47,
                31
            ],
            [
                48,
                31
            ],
            [
                49,
                31
            ],
            [
                50,
                31
            ],
            [
                51,
                31
            ],
            [
                52,
                31
            ],
            [
                53,
                31
            ],
            [
                54,
                31
            ],
            [
                55,
                31
            ],
            [
                56,
                31
            ],
            [
                57,
                31
            ],
            [
                58,
                31
            ],
            [
                59,
                32
            ],
            [
                60,
                32
            ],
            [
                61,
                32
            ],
            [
                62,
                32
            ],
            [
                63,
                32
            ],
            [
                64,
                32
            ],
            [
                65,
                32
            ],
            [
                66,
                32
            ],
            [
                67,
                32
            ],
            [
                68,
                32
            ],
            [
                69,
                32
            ],
            [
                70,
                32
            ],
            [
                71,
                32
            ],
            [
                72,
                32
            ],
            [
                73,
                32
            ],
            [
                74,
                32
            ],
            [
                75,
                32
            ],
            [
                76,
                32
            ],
            [
                77,
                32
            ],
            [
                78,
                32
            ],
            [
                79,
                32
            ],
            [
                80,
                32
            ],
            [
                81,
                32
            ],
            [
                82,
                32
            ],
            [
                83,
                32
            ],
            [
                84,
                32
            ],
            [
                85,
                32
            ],
            [
                86,
                32
            ],
            [
                87,
                32
            ],
            [
                88,
                32
            ],
            [
                89,
                32
            ],
            [
                90,
                32
            ],
            [
                91,
                32
            ],
            [
                92,
                32
            ],
            [
                93,
                32
            ],
            [
                94,
                32
            ],
            [
                95,
                32
            ],
            [
                96,
                32
            ],
            [
                97,
                32
            ],
            [
                98,
                32
            ],
            [
                99,
                32
            ],
            [
                100,
                32
            ],
            [
                101,
                32
            ],
            [
                102,
                32
            ],
            [
                103,
                32
            ],
            [
                104,
                32
            ],
            [
                105,
                32
            ],
            [
                106,
                32
            ],
            [
                107,
                32
            ],
            [
                108,
                32
            ],
            [
                109,
                32
            ],
            [
                110,
                32
            ],
            [
                111,
                32
            ],
            [
                112,
                32
            ],
            [
                113,
                32
            ],
            [
                114,
                32
            ],
            [
                115,
                32
            ],
            [
                116,
                32
            ],
            [
                117,
                32
            ],
            [
                118,
                32
            ],
            [
                119,
                32
            ],
            [
                120,
                32
            ],
            [
                121,
                32
            ],
            [
                122,
                32
            ],
            [
                123,
                32
            ],
            [
                124,
                32
            ],
            [
                125,
                32
            ],
            [
                126,
                32
            ],
            [
                127,
                32
            ],
            [
                128,
                32
            ],
            [
                129,
                32
            ],
            [
                130,
                32
            ],
            [
                131,
                32
            ],
            [
                132,
                32
            ],
            [
                133,
                32
            ],
            [
                134,
                32
            ],
            [
                135,
                32
            ],
            [
                136,
                32
            ],
            [
                137,
                32
            ],
            [
                138,
                32
            ],
            [
                139,
                32
            ],
            [
                140,
                32
            ],
            [
                141,
                32
            ],
            [
                142,
                32
            ],
            [
                143,
                32
            ],
            [
                144,
                32
            ],
            [
                145,
                32
            ],
            [
                146,
                32
            ],
            [
                147,
                32
            ],
            [
                148,
                32
            ],
            [
                149,
                32
            ],
            [
                150,
                32
            ],
            [
                151,
                32
            ],
            [
                152,
                32
            ],
            [
                153,
                32
            ],
            [
                154,
                32
            ],
            [
                155,
                32
            ],
            [
                156,
                32
            ],
            [
                157,
                32
            ],
            [
                158,
                32
            ],
            [
                159,
                32
            ],
            [
                160,
                32
            ],
            [
                161,
                32
            ],
            [
                162,
                32
            ],
            [
                163,
                32
            ],
            [
                164,
                32
            ],
            [
                165,
                32
            ],
            [
                166,
                32
            ],
            [
                167,
                32
            ],
            [
                168,
                32
            ],
            [
                169,
                32
            ],
            [
                170,
                32
            ],
            [
                171,
                32
            ],
            [
                172,
                32
            ],
            [
                173,
                32
            ],
            [
                174,
                32
            ],
            [
                175,
                32
            ],
            [
                176,
                32
            ],
            [
                177,
                32
            ],
            [
                178,
                32
            ],
            [
                179,
                32
            ],
            [
                180,
                32
            ],
            [
                181,
                32
            ],
            [
                182,
                32
            ],
            [
                183,
                32
            ],
            [
                184,
                32
            ],
            [
                185,
                32
            ],
            [
                186,
                32
            ],
            [
                187,
                32
            ],
            [
                188,
                32
            ],
            [
                189,
                32
            ],
            [
                190,
                32
            ],
            [
                191,
                32
            ],
            [
                192,
                32
            ],
            [
                193,
                32
            ],
            [
                194,
                32
            ],
            [
                195,
                32
            ],
            [
                196,
                32
            ],
            [
                197,
                32
            ],
            [
                198,
                32
            ],
            [
                199,
                32
            ],
            [
                200,
                32
            ],
            [
                201,
                32
            ],
            [
                202,
                32
            ],
            [
                203,
                32
            ],
            [
                204,
                32
            ],
            [
                205,
                32
            ],
            [
                206,
                32
            ],
            [
                207,
                32
            ],
            [
                208,
                32
            ],
            [
                209,
                32
            ],
            [
                210,
                32
            ],
            [
                211,
                32
            ],
            [
                212,
                32
            ],
            [
                213,
                32
            ],
            [
                214,
                32
            ],
            [
                215,
                32
            ],
            [
                216,
                32
            ],
            [
                217,
                32
            ],
            [
                218,
                32
            ],
            [
                219,
                32
            ],
            [
                220,
                32
            ],
            [
                221,
                32
            ],
            [
                222,
                32
            ],
            [
                223,
                32
            ],
            [
                224,
                32
            ],
            [
                225,
                32
            ],
            [
                226,
                32
            ],
            [
                227,
                32
            ],
            [
                228,
                32
            ],
            [
                229,
                32
            ],
            [
                230,
                32
            ],
            [
                231,
                32
            ],
            [
                232,
                32
            ],
            [
                233,
                32
            ],
            [
                234,
                32
            ],
            [
                235,
                32
            ],
            [
                236,
                32
            ],
            [
                237,
                32
            ],
            [
                238,
                32
            ],
            [
                239,
                32
            ],
            [
                240,
                32
            ],
            [
                241,
                32
            ],
            [
                242,
                32
            ],
            [
                243,
                32
            ],
            [
                244,
                32
            ],
            [
                245,
                32
            ],
            [
                246,
                32
            ],
            [
                247,
                32
            ],
            [
                248,
                32
            ],
            [
                249,
                32
            ],
            [
                250,
                32
            ],
            [
                251,
                32
            ],
            [
                252,
                32
            ],
            [
                253,
                32
            ],
            [
                254,
                32
            ],
            [
                255,
                32
            ],
            [
                256,
                32
            ],
            [
                257,
                32
            ],
            [
                258,
                32
            ],
            [
                259,
                32
            ],
            [
                260,
                32
            ],
            [
                261,
                32
            ],
            [
                262,
                32
            ],
            [
                263,
                32
            ],
            [
                264,
                32
            ],
            [
                265,
                32
            ],
            [
                266,
                32
            ],
            [
                267,
                32
            ],
            [
                268,
                32
            ],
            [
                269,
                32
            ],
            [
                270,
                32
            ],
            [
                271,
                32
            ],
            [
                272,
                32
            ],
            [
                273,
                32
            ],
            [
                274,
                32
            ],
            [
                275,
                32
            ],
            [
                276,
                32
            ],
            [
                277,
                32
            ],
            [
                278,
                32
            ],
            [
                279,
                32
            ],
            [
                280,
                32
            ],
            [
                281,
                32
            ],
            [
                282,
                32
            ],
            [
                283,
                32
            ],
            [
                284,
                32
            ],
            [
                285,
                32
            ],
            [
                286,
                32
            ],
            [
                287,
                32
            ],
            [
                288,
                32
            ],
            [
                289,
                32
            ],
            [
                290,
                32
            ],
            [
                291,
                32
            ],
            [
                292,
                32
            ],
            [
                293,
                32
            ],
            [
                294,
                32
            ],
            [
                295,
                32
            ],
            [
                296,
                32
            ],
            [
                297,
                32
            ],
            [
                298,
                32
            ],
            [
                299,
                32
            ],
            [
                300,
                32
            ],
            [
                301,
                32
            ],
            [
                302,
                32
            ],
            [
                303,
                32
            ],
            [
                304,
                32
            ],
            [
                305,
                32
            ],
            [
                306,
                32
            ],
            [
                307,
                32
            ],
            [
                308,
                32
            ],
            [
                309,
                32
            ],
            [
                310,
                32
            ],
            [
                311,
                32
            ],
            [
                312,
                32
            ],
            [
                313,
                32
            ],
            [
                314,
                32
            ],
            [
                315,
                32
            ],
            [
                316,
                32
            ],
            [
                317,
                32
            ],
            [
                318,
                32
            ],
            [
                319,
                32
            ],
            [
                320,
                32
            ],
            [
                321,
                32
            ],
            [
                322,
                32
            ],
            [
                323,
                32
            ],
            [
                324,
                32
            ],
            [
                325,
                32
            ],
            [
                326,
                32
            ],
            [
                327,
                32
            ],
            [
                328,
                32
            ],
            [
                329,
                32
            ],
            [
                330,
                32
            ],
            [
                331,
                32
            ],
            [
                332,
                32
            ],
            [
                333,
                32
            ],
            [
                334,
                32
            ],
            [
                335,
                32
            ],
            [
                336,
                32
            ],
            [
                337,
                32
            ],
            [
                338,
                32
            ],
            [
                339,
                33
            ],
            [
                340,
                33
            ],
            [
                341,
                33
            ],
            [
                342,
                34
            ],
            [
                343,
                34
            ],
            [
                344,
                35
            ],
            [
                345,
                35
            ],
            [
                346,
                35
            ],
            [
                347,
                36
            ],
            [
                348,
                36
            ],
            [
                349,
                37
            ],
            [
                350,
                37
            ],
            [
                351,
                37
            ],
            [
                352,
                38
            ],
            [
                353,
                38
            ],
            [
                354,
                39
            ],
            [
                355,
                39
            ],
            [
                356,
                39
            ],
            [
                357,
                40
            ],
            [
                358,
                40
            ],
            [
                359,
                41
            ],
            [
                360,
                41
            ],
            [
                361,
                42
            ],
            [
                362,
                42
            ],
            [
                363,
                43
            ],
            [
                364,
                43
            ],
            [
                365,
                44
            ],
            [
                366,
                44
            ],
            [
                367,
                45
            ],
            [
                368,
                45
            ],
            [
                369,
                46
            ],
            [
                370,
                46
            ],
            [
                371,
                46
            ],
            [
                372,
                47
            ],
            [
                373,
                47
            ],
            [
                374,
                48
            ],
            [
                375,
                48
            ],
            [
                376,
                48
            ],
            [
                377,
                49
            ],
            [
                378,
                49
            ],
            [
                379,
                50
            ],
            [
                380,
                50
            ],
            [
                381,
                51
            ],
            [
                382,
                51
            ],
            [
                383,
                52
            ],
            [
                384,
                52
            ],
            [
                385,
                53
            ],
            [
                386,
                53
            ],
            [
                387,
                54
            ],
            [
                388,
                54
            ],
            [
                389,
                55
            ],
            [
                390,
                55
            ],
            [
                391,
                55
            ],
            [
                392,
                56
            ],
            [
                393,
                56
            ],
            [
                394,
                57
            ],
            [
                395,
                57
            ],
            [
                396,
                57
            ],
            [
                397,
                58
            ],
            [
                398,
                58
            ],
            [
                399,
                59
            ],
            [
                400,
                59
            ],
            [
                401,
                60
            ],
            [
                402,
                60
            ],
            [
                403,
                61
            ],
            [
                404,
                61
            ],
            [
                405,
                62
            ],
            [
                406,
                62
            ],
            [
                407,
                63
            ],
            [
                408,
                63
            ],
            [
                409,
                64
            ],
            [
                410,
                64
            ],
            [
                411,
                65
            ],
            [
                412,
                65
            ],
            [
                413,
                66
            ],
            [
                414,
                66
            ],
            [
                415,
                67
            ],
            [
                416,
                67
            ],
            [
                417,
                68
            ],
            [
                418,
                68
            ],
            [
                419,
                69
            ],
            [
                420,
                69
            ],
            [
                421,
                69
            ],
            [
                422,
                70
            ],
            [
                423,
                70
            ],
            [
                424,
                71
            ],
            [
                425,
                71
            ],
            [
                426,
                71
            ],
            [
                427,
                72
            ],
            [
                428,
                72
            ],
            [
                429,
                73
            ],
            [
                430,
                73
            ],
            [
                431,
                74
            ],
            [
                432,
                74
            ],
            [
                433,
                75
            ],
            [
                434,
                75
            ],
            [
                435,
                76
            ],
            [
                436,
                76
            ],
            [
                437,
                77
            ],
            [
                438,
                77
            ],
            [
                439,
                78
            ],
            [
                440,
                78
            ],
            [
                441,
                79
            ],
            [
                442,
                79
            ],
            [
                443,
                80
            ],
            [
                444,
                80
            ],
            [
                445,
                81
            ],
            [
                446,
                81
            ],
            [
                447,
                82
            ],
            [
                448,
                82
            ],
            [
                449,
                83
            ],
            [
                450,
                83
            ],
            [
                451,
                83
            ],
            [
                452,
                84
            ],
            [
                453,
                84
            ],
            [
                454,
                85
            ],
            [
                455,
                85
            ],
            [
                456,
                85
            ],
            [
                457,
                86
            ],
            [
                458,
                86
            ],
            [
                459,
                87
            ],
            [
                460,
                87
            ],
            [
                461,
                88
            ],
            [
                462,
                88
            ],
            [
                463,
                89
            ],
            [
                464,
                89
            ],
            [
                465,
                90
            ],
            [
                466,
                90
            ],
            [
                467,
                91
            ],
            [
                468,
                91
            ],
            [
                469,
                92
            ],
            [
                470,
                92
            ],
            [
                471,
                93
            ],
            [
                472,
                93
            ],
            [
                473,
                94
            ],
            [
                474,
                95
            ],
            [
                475,
                95
            ],
            [
                476,
                96
            ],
            [
                477,
                96
            ],
            [
                478,
                97
            ],
            [
                479,
                98
            ],
            [
                480,
                98
            ],
            [
                481,
                98
            ],
            [
                482,
                99
            ],
            [
                483,
                99
            ],
            [
                484,
                100
            ],
            [
                485,
                100
            ],
            [
                486,
                100
            ],
            [
                487,
                101
            ],
            [
                488,
                101
            ],
            [
                489,
                102
            ],
            [
                490,
                102
            ],
            [
                491,
                103
            ],
            [
                492,
                103
            ],
            [
                493,
                104
            ],
            [
                494,
                104
            ],
            [
                495,
                105
            ],
            [
                496,
                105
            ],
            [
                497,
                106
            ],
            [
                498,
                106
            ],
            [
                499,
                107
            ],
            [
                500,
                107
            ],
            [
                501,
                108
            ],
            [
                502,
                108
            ],
            [
                503,
                109
            ],
            [
                504,
                110
            ],
            [
                505,
                110
            ],
            [
                506,
                111
            ],
            [
                507,
                111
            ],
            [
                508,
                112
            ],
            [
                509,
                113
            ],
            [
                510,
                113
            ],
            [
                511,
                114
            ],
            [
                512,
                114
            ],
            [
                513,
                115
            ],
            [
                514,
                115
            ],
            [
                515,
                116
            ],
            [
                516,
                116
            ],
            [
                517,
                117
            ],
            [
                518,
                117
            ],
            [
                519,
                118
            ],
            [
                520,
                118
            ],
            [
                521,
                119
            ],
            [
                522,
                119
            ],
            [
                523,
                120
            ],
            [
                524,
                120
            ],
            [
                525,
                121
            ],
            [
                526,
                121
            ],
            [
                527,
                122
            ],
            [
                528,
                122
            ],
            [
                529,
                123
            ],
            [
                530,
                123
            ],
            [
                531,
                124
            ],
            [
                532,
                124
            ],
            [
                533,
                125
            ],
            [
                534,
                126
            ],
            [
                535,
                126
            ],
            [
                536,
                127
            ],
            [
                537,
                127
            ],
            [
                538,
                128
            ],
            [
                539,
                129
            ],
            [
                540,
                129
            ],
            [
                541,
                130
            ],
            [
                542,
                130
            ],
            [
                543,
                131
            ],
            [
                544,
                131
            ],
            [
                545,
                132
            ],
            [
                546,
                132
            ],
            [
                547,
                133
            ],
            [
                548,
                133
            ],
            [
                549,
                134
            ],
            [
                550,
                134
            ],
            [
                551,
                135
            ],
            [
                552,
                135
            ],
            [
                553,
                136
            ],
            [
                554,
                137
            ],
            [
                555,
                137
            ],
            [
                556,
                138
            ],
            [
                557,
                138
            ],
            [
                558,
                139
            ],
            [
                559,
                140
            ],
            [
                560,
                140
            ],
            [
                561,
                141
            ],
            [
                562,
                141
            ],
            [
                563,
                142
            ],
            [
                564,
                142
            ],
            [
                565,
                143
            ],
            [
                566,
                143
            ],
            [
                567,
                144
            ],
            [
                568,
                144
            ],
            [
                569,
                145
            ],
            [
                570,
                145
            ],
            [
                571,
                146
            ],
            [
                572,
                147
            ],
            [
                573,
                147
            ],
            [
                574,
                148
            ],
            [
                575,
                149
            ],
            [
                576,
                149
            ],
            [
                577,
                150
            ],
            [
                578,
                151
            ],
            [
                579,
                152
            ],
            [
                580,
                152
            ],
            [
                581,
                153
            ],
            [
                582,
                153
            ],
            [
                583,
                154
            ],
            [
                584,
                155
            ],
            [
                585,
                155
            ],
            [
                586,
                156
            ],
            [
                587,
                156
            ],
            [
                588,
                157
            ],
            [
                589,
                158
            ],
            [
                590,
                158
            ],
            [
                591,
                159
            ],
            [
                592,
                159
            ],
            [
                593,
                160
            ],
            [
                594,
                160
            ],
            [
                595,
                161
            ],
            [
                596,
                161
            ],
            [
                597,
                162
            ],
            [
                598,
                162
            ],
            [
                599,
                163
            ],
            [
                600,
                163
            ],
            [
                601,
                164
            ],
            [
                602,
                164
            ],
            [
                603,
                165
            ],
            [
                604,
                166
            ],
            [
                605,
                166
            ],
            [
                606,
                167
            ],
            [
                607,
                167
            ],
            [
                608,
                168
            ],
            [
                609,
                169
            ],
            [
                610,
                169
            ],
            [
                611,
                170
            ],
            [
                612,
                171
            ],
            [
                613,
                171
            ],
            [
                614,
                172
            ],
            [
                615,
                173
            ],
            [
                616,
                173
            ],
            [
                617,
                174
            ],
            [
                618,
                175
            ],
            [
                619,
                176
            ],
            [
                620,
                176
            ],
            [
                621,
                177
            ],
            [
                622,
                177
            ],
            [
                623,
                178
            ],
            [
                624,
                179
            ],
            [
                625,
                179
            ],
            [
                626,
                180
            ],
            [
                627,
                180
            ],
            [
                628,
                181
            ],
            [
                629,
                182
            ],
            [
                630,
                182
            ],
            [
                631,
                183
            ],
            [
                632,
                184
            ],
            [
                633,
                184
            ],
            [
                634,
                185
            ],
            [
                635,
                186
            ],
            [
                636,
                186
            ],
            [
                637,
                187
            ],
            [
                638,
                188
            ],
            [
                639,
                189
            ],
            [
                640,
                189
            ],
            [
                641,
                190
            ],
            [
                642,
                190
            ],
            [
                643,
                191
            ],
            [
                644,
                192
            ],
            [
                645,
                192
            ],
            [
                646,
                193
            ],
            [
                647,
                193
            ],
            [
                648,
                194
            ],
            [
                649,
                195
            ],
            [
                650,
                195
            ],
            [
                651,
                196
            ],
            [
                652,
                197
            ],
            [
                653,
                197
            ],
            [
                654,
                198
            ],
            [
                655,
                199
            ],
            [
                656,
                199
            ],
            [
                657,
                200
            ],
            [
                658,
                201
            ],
            [
                659,
                202
            ],
            [
                660,
                202
            ],
            [
                661,
                203
            ],
            [
                662,
                204
            ],
            [
                663,
                204
            ],
            [
                664,
                205
            ],
            [
                665,
                206
            ],
            [
                666,
                206
            ],
            [
                667,
                207
            ],
            [
                668,
                208
            ],
            [
                669,
                209
            ],
            [
                670,
                209
            ],
            [
                671,
                210
            ],
            [
                672,
                211
            ],
            [
                673,
                211
            ],
            [
                674,
                212
            ],
            [
                675,
                213
            ],
            [
                676,
                213
            ],
            [
                677,
                214
            ],
            [
                678,
                215
            ],
            [
                679,
                216
            ],
            [
                680,
                216
            ],
            [
                681,
                217
            ],
            [
                682,
                218
            ],
            [
                683,
                218
            ],
            [
                684,
                219
            ],
            [
                685,
                220
            ],
            [
                686,
                220
            ],
            [
                687,
                221
            ],
            [
                688,
                222
            ],
            [
                689,
                223
            ],
            [
                690,
                223
            ],
            [
                691,
                224
            ],
            [
                692,
                225
            ],
            [
                693,
                226
            ],
            [
                694,
                227
            ],
            [
                695,
                227
            ],
            [
                696,
                228
            ],
            [
                697,
                229
            ],
            [
                698,
                230
            ],
            [
                699,
                231
            ],
            [
                700,
                231
            ],
            [
                701,
                232
            ],
            [
                702,
                233
            ],
            [
                703,
                234
            ],
            [
                704,
                235
            ],
            [
                705,
                235
            ],
            [
                706,
                236
            ],
            [
                707,
                237
            ],
            [
                708,
                238
            ],
            [
                709,
                239
            ],
            [
                710,
                239
            ],
            [
                711,
                240
            ],
            [
                712,
                241
            ],
            [
                713,
                242
            ],
            [
                714,
                243
            ],
            [
                715,
                243
            ],
            [
                716,
                244
            ],
            [
                717,
                245
            ],
            [
                718,
                246
            ],
            [
                719,
                247
            ],
            [
                720,
                247
            ],
            [
                721,
                248
            ],
            [
                722,
                249
            ],
            [
                723,
                250
            ],
            [
                724,
                251
            ],
            [
                725,
                251
            ],
            [
                726,
                252
            ],
            [
                727,
                253
            ],
            [
                728,
                254
            ],
            [
                729,
                255
            ],
            [
                730,
                255
            ],
            [
                731,
                256
            ],
            [
                732,
                257
            ],
            [
                733,
                258
            ],
            [
                734,
                259
            ],
            [
                735,
                259
            ],
            [
                736,
                260
            ],
            [
                737,
                261
            ],
            [
                738,
                262
            ],
            [
                739,
                263
            ],
            [
                740,
                263
            ],
            [
                741,
                264
            ],
            [
                742,
                265
            ],
            [
                743,
                266
            ],
            [
                744,
                267
            ],
            [
                745,
                268
            ],
            [
                746,
                269
            ],
            [
                747,
                270
            ],
            [
                748,
                271
            ],
            [
                749,
                272
            ],
            [
                750,
                272
            ],
            [
                751,
                273
            ],
            [
                752,
                274
            ],
            [
                753,
                275
            ],
            [
                754,
                276
            ],
            [
                755,
                276
            ],
            [
                756,
                277
            ],
            [
                757,
                278
            ],
            [
                758,
                279
            ],
            [
                759,
                280
            ],
            [
                760,
                280
            ],
            [
                761,
                281
            ],
            [
                762,
                282
            ],
            [
                763,
                283
            ],
            [
                764,
                284
            ],
            [
                765,
                285
            ],
            [
                766,
                286
            ],
            [
                767,
                287
            ],
            [
                768,
                288
            ],
            [
                769,
                289
            ],
            [
                770,
                290
            ],
            [
                771,
                291
            ],
            [
                772,
                292
            ],
            [
                773,
                293
            ],
            [
                774,
                294
            ],
            [
                775,
                295
            ],
            [
                776,
                296
            ],
            [
                777,
                297
            ],
            [
                778,
                298
            ],
            [
                779,
                299
            ],
            [
                780,
                299
            ],
            [
                781,
                300
            ],
            [
                782,
                301
            ],
            [
                783,
                302
            ],
            [
                784,
                303
            ],
            [
                785,
                304
            ],
            [
                786,
                305
            ],
            [
                787,
                306
            ],
            [
                788,
                307
            ],
            [
                789,
                308
            ],
            [
                790,
                309
            ],
            [
                791,
                310
            ],
            [
                792,
                311
            ],
            [
                793,
                312
            ],
            [
                794,
                313
            ],
            [
                795,
                314
            ],
            [
                796,
                315
            ],
            [
                797,
                316
            ],
            [
                798,
                317
            ],
            [
                799,
                318
            ],
            [
                800,
                319
            ],
            [
                801,
                320
            ],
            [
                802,
                321
            ],
            [
                803,
                322
            ],
            [
                804,
                324
            ],
            [
                805,
                325
            ],
            [
                806,
                326
            ],
            [
                807,
                327
            ],
            [
                808,
                328
            ],
            [
                809,
                330
            ],
            [
                810,
                331
            ],
            [
                811,
                332
            ],
            [
                812,
                333
            ],
            [
                813,
                334
            ],
            [
                814,
                335
            ],
            [
                815,
                336
            ],
            [
                816,
                337
            ],
            [
                817,
                338
            ],
            [
                818,
                339
            ],
            [
                819,
                340
            ],
            [
                820,
                341
            ],
            [
                821,
                342
            ],
            [
                822,
                343
            ],
            [
                823,
                344
            ],
            [
                824,
                346
            ],
            [
                825,
                347
            ],
            [
                826,
                348
            ],
            [
                827,
                349
            ],
            [
                828,
                350
            ],
            [
                829,
                352
            ],
            [
                830,
                353
            ],
            [
                831,
                354
            ],
            [
                832,
                355
            ],
            [
                833,
                356
            ],
            [
                834,
                358
            ],
            [
                835,
                359
            ],
            [
                836,
                360
            ],
            [
                837,
                361
            ],
            [
                838,
                362
            ],
            [
                839,
                364
            ],
            [
                840,
                365
            ],
            [
                841,
                366
            ],
            [
                842,
                367
            ],
            [
                843,
                369
            ],
            [
                844,
                370
            ],
            [
                845,
                371
            ],
            [
                846,
                373
            ],
            [
                847,
                374
            ],
            [
                848,
                375
            ],
            [
                849,
                377
            ],
            [
                850,
                378
            ],
            [
                851,
                379
            ],
            [
                852,
                381
            ],
            [
                853,
                382
            ],
            [
                854,
                384
            ],
            [
                855,
                385
            ],
            [
                856,
                386
            ],
            [
                857,
                388
            ],
            [
                858,
                389
            ],
            [
                859,
                391
            ],
            [
                860,
                392
            ],
            [
                861,
                394
            ],
            [
                862,
                395
            ],
            [
                863,
                397
            ],
            [
                864,
                398
            ],
            [
                865,
                400
            ],
            [
                866,
                401
            ],
            [
                867,
                403
            ],
            [
                868,
                404
            ],
            [
                869,
                406
            ],
            [
                870,
                407
            ],
            [
                871,
                409
            ],
            [
                872,
                410
            ],
            [
                873,
                412
            ],
            [
                874,
                413
            ],
            [
                875,
                415
            ],
            [
                876,
                416
            ],
            [
                877,
                418
            ],
            [
                878,
                419
            ],
            [
                879,
                421
            ],
            [
                880,
                422
            ],
            [
                881,
                424
            ],
            [
                882,
                426
            ],
            [
                883,
                427
            ],
            [
                884,
                429
            ],
            [
                885,
                431
            ],
            [
                886,
                432
            ],
            [
                887,
                434
            ],
            [
                888,
                436
            ],
            [
                889,
                438
            ],
            [
                890,
                439
            ],
            [
                891,
                441
            ],
            [
                892,
                443
            ],
            [
                893,
                445
            ],
            [
                894,
                447
            ],
            [
                895,
                449
            ],
            [
                896,
                451
            ],
            [
                897,
                453
            ],
            [
                898,
                455
            ],
            [
                899,
                457
            ],
            [
                900,
                459
            ],
            [
                901,
                461
            ],
            [
                902,
                463
            ],
            [
                903,
                466
            ],
            [
                904,
                468
            ],
            [
                905,
                470
            ],
            [
                906,
                473
            ],
            [
                907,
                475
            ],
            [
                908,
                477
            ],
            [
                909,
                480
            ],
            [
                910,
                482
            ],
            [
                911,
                485
            ],
            [
                912,
                487
            ],
            [
                913,
                490
            ],
            [
                914,
                493
            ],
            [
                915,
                495
            ],
            [
                916,
                498
            ],
            [
                917,
                500
            ],
            [
                918,
                503
            ],
            [
                919,
                506
            ],
            [
                920,
                509
            ],
            [
                921,
                512
            ],
            [
                922,
                515
            ],
            [
                923,
                519
            ],
            [
                924,
                522
            ],
            [
                925,
                525
            ],
            [
                926,
                529
            ],
            [
                927,
                532
            ],
            [
                928,
                535
            ],
            [
                929,
                539
            ],
            [
                930,
                543
            ],
            [
                931,
                548
            ],
            [
                932,
                552
            ],
            [
                933,
                557
            ],
            [
                934,
                561
            ],
            [
                935,
                566
            ],
            [
                936,
                570
            ],
            [
                937,
                575
            ],
            [
                938,
                579
            ],
            [
                939,
                584
            ]
        ]
    ],
    "ocr_results": [
        {
            "text": "Drain-Source Continous Current, IDS (DC) (A)",
            "bbox": [
                21,
                95,
                60,
                636
            ],
            "conf": 0.0,
            "words": [
                {
                    "text": "Drain",
                    "bbox": [
                        21,
                        568,
                        56,
                        636
                    ],
                    "confidence": 0.0
                },
                {
                    "text": "-",
                    "bbox": [
                        22,
                        558,
                        55,
                        566
                    ],
                    "confidence": 0.0
                },
                {
                    "text": "Source",
                    "bbox": [
                        22,
                        469,
                        57,
                        558
                    ],
                    "confidence": 0.0
                },
                {
                    "text": "Continous",
                    "bbox": [
                        23,
                        331,
                        58,
                        462
                    ],
                    "confidence": 0.0
                },
                {
                    "text": "Current",
                    "bbox": [
                        24,
                        225,
                        59,
                        325
                    ],
                    "confidence": 0.0
                },
                {
                    "text": ",",
                    "bbox": [
                        26,
                        219,
                        59,
                        225
                    ],
                    "confidence": 0.0
                },
                {
                    "text": "IDS",
                    "bbox": [
                        26,
                        181,
                        59,
                        211
                    ],
                    "confidence": 0.0
                },
                {
                    "text": "(",
                    "bbox": [
                        26,
                        168,
                        59,
                        176
                    ],
                    "confidence": 0.0
                },
                {
                    "text": "DC",
                    "bbox": [
                        26,
                        143,
                        59,
                        169
                    ],
                    "confidence": 0.0
                },
                {
                    "text": ")",
                    "bbox": [
                        27,
                        137,
                        60,
                        145
                    ],
                    "confidence": 0.0
                },
                {
                    "text": "(",
                    "bbox": [
                        27,
                        121,
                        60,
                        131
                    ],
                    "confidence": 0.0
                },
                {
                    "text": "A",
                    "bbox": [
                        27,
                        103,
                        60,
                        124
                    ],
                    "confidence": 0.0
                },
                {
                    "text": ")",
                    "bbox": [
                        27,
                        95,
                        60,
                        106
                    ],
                    "confidence": 0.0
                }
            ],
            "associated_element": "y_axis"
        },
        {
            "text": "120",
            "bbox": [
                72,
                29,
                114,
                48
            ],
            "conf": 0.0,
            "words": [
                {
                    "text": "120",
                    "bbox": [
                        72,
                        29,
                        114,
                        48
                    ],
                    "confidence": 0.0
                }
            ],
            "associated_element": "y_axis"
        },
        {
            "text": "100",
            "bbox": [
                72,
                133,
                114,
                152
            ],
            "conf": 0.0,
            "words": [
                {
                    "text": "100",
                    "bbox": [
                        72,
                        133,
                        114,
                        152
                    ],
                    "confidence": 0.0
                }
            ],
            "associated_element": "y_axis"
        },
        {
            "text": "Conditions:",
            "bbox": [
                938,
                67,
                1056,
                84
            ],
            "conf": 0.0,
            "words": [
                {
                    "text": "Conditions",
                    "bbox": [
                        938,
                        67,
                        1049,
                        84
                    ],
                    "confidence": 0.0
                },
                {
                    "text": ":",
                    "bbox": [
                        1050,
                        67,
                        1056,
                        84
                    ],
                    "confidence": 0.0
                }
            ],
            "associated_element": "legend_box"
        },
        {
            "text": "T, \u2264 175 \u00b0C",
            "bbox": [
                937,
                96,
                1047,
                118
            ],
            "conf": 0.0,
            "words": [
                {
                    "text": "T",
                    "bbox": [
                        937,
                        99,
                        951,
                        118
                    ],
                    "confidence": 0.0
                },
                {
                    "text": ",",
                    "bbox": [
                        949,
                        98,
                        954,
                        117
                    ],
                    "confidence": 0.0
                },
                {
                    "text": "\u2264",
                    "bbox": [
                        961,
                        98,
                        973,
                        117
                    ],
                    "confidence": 0.0
                },
                {
                    "text": "175",
                    "bbox": [
                        982,
                        96,
                        1019,
                        117
                    ],
                    "confidence": 0.0
                },
                {
                    "text": "\u00b0",
                    "bbox": [
                        1026,
                        97,
                        1034,
                        116
                    ],
                    "confidence": 0.0
                },
                {
                    "text": "C",
                    "bbox": [
                        1034,
                        97,
                        1047,
                        116
                    ],
                    "confidence": 0.0
                }
            ],
            "associated_element": "legend_box"
        },
        {
            "text": "80",
            "bbox": [
                86,
                242,
                113,
                257
            ],
            "conf": 0.0,
            "words": [
                {
                    "text": "80",
                    "bbox": [
                        86,
                        242,
                        113,
                        257
                    ],
                    "confidence": 0.0
                }
            ],
            "associated_element": "y_axis"
        },
        {
            "text": "60",
            "bbox": [
                87,
                347,
                116,
                363
            ],
            "conf": 0.0,
            "words": [
                {
                    "text": "60",
                    "bbox": [
                        87,
                        347,
                        116,
                        363
                    ],
                    "confidence": 0.0
                }
            ],
            "associated_element": "y_axis"
        },
        {
            "text": "10",
            "bbox": [
                89,
                446,
                112,
                479
            ],
            "conf": 0.0,
            "words": [
                {
                    "text": "10",
                    "bbox": [
                        89,
                        446,
                        112,
                        479
                    ],
                    "confidence": 0.0
                }
            ],
            "associated_element": "y_axis"
        },
        {
            "text": "40",
            "bbox": [
                85,
                452,
                114,
                468
            ],
            "conf": 0.0,
            "words": [
                {
                    "text": "40",
                    "bbox": [
                        85,
                        452,
                        114,
                        468
                    ],
                    "confidence": 0.0
                }
            ],
            "associated_element": "y_axis"
        },
        {
            "text": "20",
            "bbox": [
                86,
                558,
                115,
                573
            ],
            "conf": 0.0,
            "words": [
                {
                    "text": "20",
                    "bbox": [
                        86,
                        558,
                        115,
                        573
                    ],
                    "confidence": 0.0
                }
            ],
            "associated_element": "y_axis"
        },
        {
            "text": "0",
            "bbox": [
                100,
                663,
                116,
                679
            ],
            "conf": 0.0,
            "words": [
                {
                    "text": "0",
                    "bbox": [
                        100,
                        663,
                        116,
                        679
                    ],
                    "confidence": 0.0
                }
            ],
            "associated_element": "y_axis"
        },
        {
            "text": "-55",
            "bbox": [
                124,
                700,
                161,
                715
            ],
            "conf": 0.0,
            "words": [
                {
                    "text": "-55",
                    "bbox": [
                        124,
                        700,
                        161,
                        715
                    ],
                    "confidence": 0.0
                }
            ],
            "associated_element": "x_axis"
        },
        {
            "text": "-30",
            "bbox": [
                224,
                697,
                265,
                717
            ],
            "conf": 0.0,
            "words": [
                {
                    "text": "-30",
                    "bbox": [
                        224,
                        697,
                        265,
                        717
                    ],
                    "confidence": 0.0
                }
            ],
            "associated_element": "x_axis"
        },
        {
            "text": "-5",
            "bbox": [
                334,
                700,
                355,
                715
            ],
            "conf": 0.0,
            "words": [
                {
                    "text": "-5",
                    "bbox": [
                        334,
                        700,
                        355,
                        715
                    ],
                    "confidence": 0.0
                }
            ],
            "associated_element": "x_axis"
        },
        {
            "text": "20",
            "bbox": [
                432,
                700,
                462,
                716
            ],
            "conf": 0.0,
            "words": [
                {
                    "text": "20",
                    "bbox": [
                        432,
                        700,
                        462,
                        716
                    ],
                    "confidence": 0.0
                }
            ],
            "associated_element": "x_axis"
        },
        {
            "text": "45",
            "bbox": [
                532,
                701,
                559,
                716
            ],
            "conf": 0.0,
            "words": [
                {
                    "text": "45",
                    "bbox": [
                        532,
                        701,
                        559,
                        716
                    ],
                    "confidence": 0.0
                }
            ],
            "associated_element": "x_axis"
        },
        {
            "text": "70",
            "bbox": [
                634,
                700,
                665,
                716
            ],
            "conf": 0.0,
            "words": [
                {
                    "text": "70",
                    "bbox": [
                        634,
                        700,
                        665,
                        716
                    ],
                    "confidence": 0.0
                }
            ],
            "associated_element": "x_axis"
        },
        {
            "text": "95",
            "bbox": [
                735,
                700,
                764,
                716
            ],
            "conf": 0.0,
            "words": [
                {
                    "text": "95",
                    "bbox": [
                        735,
                        700,
                        764,
                        716
                    ],
                    "confidence": 0.0
                }
            ],
            "associated_element": "x_axis"
        },
        {
            "text": "120",
            "bbox": [
                830,
                700,
                873,
                716
            ],
            "conf": 0.0,
            "words": [
                {
                    "text": "120",
                    "bbox": [
                        830,
                        700,
                        873,
                        716
                    ],
                    "confidence": 0.0
                }
            ],
            "associated_element": "x_axis"
        },
        {
            "text": "145",
            "bbox": [
                933,
                700,
                974,
                716
            ],
            "conf": 0.0,
            "words": [
                {
                    "text": "145",
                    "bbox": [
                        933,
                        700,
                        974,
                        716
                    ],
                    "confidence": 0.0
                }
            ],
            "associated_element": "x_axis"
        },
        {
            "text": "170",
            "bbox": [
                1033,
                699,
                1076,
                717
            ],
            "conf": 0.0,
            "words": [
                {
                    "text": "170",
                    "bbox": [
                        1033,
                        699,
                        1076,
                        717
                    ],
                    "confidence": 0.0
                }
            ],
            "associated_element": "x_axis"
        },
        {
            "text": "Case Temperature, Tc (\u00b0C)",
            "bbox": [
                448,
                734,
                788,
                764
            ],
            "conf": 0.0,
            "words": [
                {
                    "text": "Case",
                    "bbox": [
                        448,
                        735,
                        511,
                        762
                    ],
                    "confidence": 0.0
                },
                {
                    "text": "Temperature",
                    "bbox": [
                        518,
                        734,
                        692,
                        763
                    ],
                    "confidence": 0.0
                },
                {
                    "text": ",",
                    "bbox": [
                        694,
                        736,
                        702,
                        763
                    ],
                    "confidence": 0.0
                },
                {
                    "text": "Tc",
                    "bbox": [
                        707,
                        736,
                        735,
                        763
                    ],
                    "confidence": 0.0
                },
                {
                    "text": "(",
                    "bbox": [
                        744,
                        736,
                        753,
                        763
                    ],
                    "confidence": 0.0
                },
                {
                    "text": "\u00b0",
                    "bbox": [
                        752,
                        736,
                        762,
                        763
                    ],
                    "confidence": 0.0
                },
                {
                    "text": "C",
                    "bbox": [
                        763,
                        736,
                        781,
                        763
                    ],
                    "confidence": 0.0
                },
                {
                    "text": ")",
                    "bbox": [
                        778,
                        737,
                        788,
                        764
                    ],
                    "confidence": 0.0
                }
            ],
            "associated_element": "x_axis"
        }
    ]
}