{
    "class": "0",
    "bbox": [
        1208.4908447265625,
        429.9765625,
        2211.5302734375,
        1821.424560546875
    ],
    "conf": 0.9403740763664246,
    "bbox_normalized": [
        0.4872946954542591,
        0.1226052359566581,
        0.891746077998992,
        0.5193682807376319
    ],
    "center": [
        1710.0105590820312,
        1125.7005615234375
    ],
    "center_normalized": [
        0.6895203867266255,
        0.320986758347145
    ],
    "legend_boxes": [],
    "labels": [
        {
            "class": "plot_area",
            "bbox": [
                201.14276123046875,
                271.50201416015625,
                971.8340454101562,
                1251.899169921875
            ],
            "conf": 0.8639612793922424,
            "bbox_normalized": [
                0.20054113781701768,
                0.1950445504024111,
                0.9689272636192984,
                0.89935285195537
            ]
        },
        {
            "class": "y_axis",
            "bbox": [
                33.97254180908203,
                256.2528076171875,
                196.2274932861328,
                1258.0455322265625
            ],
            "conf": 0.6190648674964905,
            "bbox_normalized": [
                0.03387092902201598,
                0.18408966064453125,
                0.19564057157141856,
                0.9037683421167834
            ]
        },
        {
            "class": "x_axis",
            "bbox": [
                197.38902282714844,
                1259.9525146484375,
                988.755126953125,
                1380.1697998046875
            ],
            "conf": 0.5452671051025391,
            "bbox_normalized": [
                0.1967986269463095,
                0.9051383007531879,
                0.9857977337518694,
                0.9915012929631376
            ]
        }
    ]
}